[
  {
    "Name": "live-like",
  	"PMCBotLimitPresets": {
      "FactoryBotLimit": 6,
      "InterchangeBotLimit": 8,
      "LaboratoryBotLimit": 6,
      "LighthouseBotLimit": 6,
      "ReserveBotLimit": 7,
      "ShorelineBotLimit": 7,
      "WoodsBotLimit": 8,
      "CustomsBotLimit": 7,
      "TarkovStreetsBotLimit": 7,
      "GroundZeroBotLimit": 8
    },
    "SCAVBotLimitPresets": {
      "FactoryBotLimit": 6,
      "InterchangeBotLimit": 8,
      "LaboratoryBotLimit": 6,
      "LighthouseBotLimit": 8,
      "ReserveBotLimit": 7,
      "ShorelineBotLimit": 7,
      "WoodsBotLimit": 10,
      "CustomsBotLimit": 7,
      "TarkovStreetsBotLimit": 7,
      "GroundZeroBotLimit": 8
    }
  },
  {
    "Name": "live-like-alt",
  	"PMCBotLimitPresets": {
      "FactoryBotLimit": 5,
      "InterchangeBotLimit": 7,
      "LaboratoryBotLimit": 5,
      "LighthouseBotLimit": 5,
      "ReserveBotLimit": 6,
      "ShorelineBotLimit": 6,
      "WoodsBotLimit": 7,
      "CustomsBotLimit": 6,
      "TarkovStreetsBotLimit": 6,
      "GroundZeroBotLimit": 7
    },
    "SCAVBotLimitPresets": {
      "FactoryBotLimit": 7,
      "InterchangeBotLimit": 9,
      "LaboratoryBotLimit": 7,
      "LighthouseBotLimit": 9,
      "ReserveBotLimit": 8,
      "ShorelineBotLimit": 8,
      "WoodsBotLimit": 11,
      "CustomsBotLimit": 8,
      "TarkovStreetsBotLimit": 8,
      "GroundZeroBotLimit": 9
    }
  },
  {
    "Name": "live-like-alt-2",
  	"PMCBotLimitPresets": {
      "FactoryBotLimit": 7,
      "InterchangeBotLimit": 9,
      "LaboratoryBotLimit": 7,
      "LighthouseBotLimit": 7,
      "ReserveBotLimit": 8,
      "ShorelineBotLimit": 8,
      "WoodsBotLimit": 9,
      "CustomsBotLimit": 8,
      "TarkovStreetsBotLimit": 8,
      "GroundZeroBotLimit": 9
    },
    "SCAVBotLimitPresets": {
      "FactoryBotLimit": 5,
      "InterchangeBotLimit": 7,
      "LaboratoryBotLimit": 5,
      "LighthouseBotLimit": 7,
      "ReserveBotLimit": 6,
      "ShorelineBotLimit": 6,
      "WoodsBotLimit": 9,
      "CustomsBotLimit": 6,
      "TarkovStreetsBotLimit": 6,
      "GroundZeroBotLimit": 7
    }
  },
  {
    "Name": "quietraids",
  	"PMCBotLimitPresets": {
      "FactoryBotLimit": 4,
      "InterchangeBotLimit": 6,
      "LaboratoryBotLimit": 4,
      "LighthouseBotLimit": 5,
      "ReserveBotLimit": 5,
      "ShorelineBotLimit": 5,
      "WoodsBotLimit": 6,
      "CustomsBotLimit": 5,
      "TarkovStreetsBotLimit": 5,
      "GroundZeroBotLimit": 6
    },
    "SCAVBotLimitPresets": {
      "FactoryBotLimit": 4,
      "InterchangeBotLimit": 6,
      "LaboratoryBotLimit": 4,
      "LighthouseBotLimit": 6,
      "ReserveBotLimit": 5,
      "ShorelineBotLimit": 5,
      "WoodsBotLimit": 6,
      "CustomsBotLimit": 5,
      "TarkovStreetsBotLimit": 5,
      "GroundZeroBotLimit": 6
    }
  },
  {
    "Name": "boss-mania",
  	"PMCBotLimitPresets": {
      "FactoryBotLimit": 6,
      "InterchangeBotLimit": 8,
      "LaboratoryBotLimit": 6,
      "LighthouseBotLimit": 6,
      "ReserveBotLimit": 7,
      "ShorelineBotLimit": 7,
      "WoodsBotLimit": 8,
      "CustomsBotLimit": 7,
      "TarkovStreetsBotLimit": 7,
      "GroundZeroBotLimit": 8
    },
    "SCAVBotLimitPresets": {
      "FactoryBotLimit": 6,
      "InterchangeBotLimit": 8,
      "LaboratoryBotLimit": 6,
      "LighthouseBotLimit": 8,
      "ReserveBotLimit": 7,
      "ShorelineBotLimit": 7,
      "WoodsBotLimit": 10,
      "CustomsBotLimit": 7,
      "TarkovStreetsBotLimit": 7,
      "GroundZeroBotLimit": 8
    }
  },
  {
    "Name": "crazyraids",
  	"PMCBotLimitPresets": {
      "FactoryBotLimit": 6,
      "InterchangeBotLimit": 8,
      "LaboratoryBotLimit": 6,
      "LighthouseBotLimit": 6,
      "ReserveBotLimit": 7,
      "ShorelineBotLimit": 7,
      "WoodsBotLimit": 8,
      "CustomsBotLimit": 7,
      "TarkovStreetsBotLimit": 7,
      "GroundZeroBotLimit": 8
    },
    "SCAVBotLimitPresets": {
      "FactoryBotLimit": 6,
      "InterchangeBotLimit": 8,
      "LaboratoryBotLimit": 6,
      "LighthouseBotLimit": 8,
      "ReserveBotLimit": 7,
      "ShorelineBotLimit": 7,
      "WoodsBotLimit": 10,
      "CustomsBotLimit": 7,
      "TarkovStreetsBotLimit": 7,
      "GroundZeroBotLimit": 8
    }
  },
  {
    "Name": "impossibleraids",
  	"PMCBotLimitPresets": {
      "FactoryBotLimit": 6,
      "InterchangeBotLimit": 8,
      "LaboratoryBotLimit": 6,
      "LighthouseBotLimit": 6,
      "ReserveBotLimit": 7,
      "ShorelineBotLimit": 7,
      "WoodsBotLimit": 8,
      "CustomsBotLimit": 7,
      "TarkovStreetsBotLimit": 7,
      "GroundZeroBotLimit": 8
    },
    "SCAVBotLimitPresets": {
      "FactoryBotLimit": 6,
      "InterchangeBotLimit": 8,
      "LaboratoryBotLimit": 6,
      "LighthouseBotLimit": 8,
      "ReserveBotLimit": 7,
      "ShorelineBotLimit": 7,
      "WoodsBotLimit": 10,
      "CustomsBotLimit": 7,
      "TarkovStreetsBotLimit": 7,
      "GroundZeroBotLimit": 8
    }
  },
  {
    "Name": "morescavs",
  	"PMCBotLimitPresets": {
      "FactoryBotLimit": 4,
      "InterchangeBotLimit": 6,
      "LaboratoryBotLimit": 4,
      "LighthouseBotLimit": 4,
      "ReserveBotLimit": 5,
      "ShorelineBotLimit": 5,
      "WoodsBotLimit": 6,
      "CustomsBotLimit": 5,
      "TarkovStreetsBotLimit": 5,
      "GroundZeroBotLimit": 6
    },
    "SCAVBotLimitPresets": {
      "FactoryBotLimit": 8,
      "InterchangeBotLimit": 10,
      "LaboratoryBotLimit": 8,
      "LighthouseBotLimit": 10,
      "ReserveBotLimit": 9,
      "ShorelineBotLimit": 9,
      "WoodsBotLimit": 12,
      "CustomsBotLimit": 9,
      "TarkovStreetsBotLimit": 9,
      "GroundZeroBotLimit": 10
    }
  },
  {
    "Name": "morepmcs",
  	"PMCBotLimitPresets": {
      "FactoryBotLimit": 8,
      "InterchangeBotLimit": 10,
      "LaboratoryBotLimit": 8,
      "LighthouseBotLimit": 8,
      "ReserveBotLimit": 9,
      "ShorelineBotLimit": 9,
      "WoodsBotLimit": 10,
      "CustomsBotLimit": 9,
      "TarkovStreetsBotLimit": 9,
      "GroundZeroBotLimit": 10
    },
    "SCAVBotLimitPresets": {
      "FactoryBotLimit": 4,
      "InterchangeBotLimit": 6,
      "LaboratoryBotLimit": 4,
      "LighthouseBotLimit": 6,
      "ReserveBotLimit": 5,
      "ShorelineBotLimit": 5,
      "WoodsBotLimit": 8,
      "CustomsBotLimit": 5,
      "TarkovStreetsBotLimit": 5,
      "GroundZeroBotLimit": 6
    }
  },
  {
    "Name": "no-starting-pmcs",
  	"PMCBotLimitPresets": {
      "FactoryBotLimit": 0,
      "InterchangeBotLimit": 0,
      "LaboratoryBotLimit": 0,
      "LighthouseBotLimit": 0,
      "ReserveBotLimit": 0,
      "ShorelineBotLimit": 0,
      "WoodsBotLimit": 0,
      "CustomsBotLimit": 0,
      "TarkovStreetsBotLimit": 0,
      "GroundZeroBotLimit": 0
    },
    "SCAVBotLimitPresets": {
      "FactoryBotLimit": 12,
      "InterchangeBotLimit": 16,
      "LaboratoryBotLimit": 12,
      "LighthouseBotLimit": 14,
      "ReserveBotLimit": 14,
      "ShorelineBotLimit": 14,
      "WoodsBotLimit": 18,
      "CustomsBotLimit": 14,
      "TarkovStreetsBotLimit": 14,
      "GroundZeroBotLimit": 16
    }
  },
  {
    "Name": "starting-pmcs-only-live-like",
  	"PMCBotLimitPresets": {
      "FactoryBotLimit": 6,
      "InterchangeBotLimit": 8,
      "LaboratoryBotLimit": 6,
      "LighthouseBotLimit": 6,
      "ReserveBotLimit": 7,
      "ShorelineBotLimit": 7,
      "WoodsBotLimit": 8,
      "CustomsBotLimit": 7,
      "TarkovStreetsBotLimit": 7,
      "GroundZeroBotLimit": 8
    },
    "SCAVBotLimitPresets": {
      "FactoryBotLimit": 6,
      "InterchangeBotLimit": 8,
      "LaboratoryBotLimit": 6,
      "LighthouseBotLimit": 8,
      "ReserveBotLimit": 7,
      "ShorelineBotLimit": 7,
      "WoodsBotLimit": 10,
      "CustomsBotLimit": 7,
      "TarkovStreetsBotLimit": 7,
      "GroundZeroBotLimit": 8
    }
  },
  {
    "Name": "starting-pmcs-only-live-like-alt",
  	"PMCBotLimitPresets": {
      "FactoryBotLimit": 6,
      "InterchangeBotLimit": 8,
      "LaboratoryBotLimit": 6,
      "LighthouseBotLimit": 6,
      "ReserveBotLimit": 7,
      "ShorelineBotLimit": 7,
      "WoodsBotLimit": 8,
      "CustomsBotLimit": 7,
      "TarkovStreetsBotLimit": 7,
      "GroundZeroBotLimit": 8
    },
    "SCAVBotLimitPresets": {
      "FactoryBotLimit": 6,
      "InterchangeBotLimit": 8,
      "LaboratoryBotLimit": 6,
      "LighthouseBotLimit": 8,
      "ReserveBotLimit": 7,
      "ShorelineBotLimit": 7,
      "WoodsBotLimit": 10,
      "CustomsBotLimit": 7,
      "TarkovStreetsBotLimit": 7,
      "GroundZeroBotLimit": 8
    }
  },
  {
    "Name": "starting-pmcs-only-morescavs",
  	"PMCBotLimitPresets": {
      "FactoryBotLimit": 6,
      "InterchangeBotLimit": 8,
      "LaboratoryBotLimit": 6,
      "LighthouseBotLimit": 6,
      "ReserveBotLimit": 7,
      "ShorelineBotLimit": 7,
      "WoodsBotLimit": 8,
      "CustomsBotLimit": 7,
      "TarkovStreetsBotLimit": 7,
      "GroundZeroBotLimit": 8
    },
    "SCAVBotLimitPresets": {
      "FactoryBotLimit": 6,
      "InterchangeBotLimit": 8,
      "LaboratoryBotLimit": 6,
      "LighthouseBotLimit": 8,
      "ReserveBotLimit": 7,
      "ShorelineBotLimit": 7,
      "WoodsBotLimit": 10,
      "CustomsBotLimit": 7,
      "TarkovStreetsBotLimit": 7,
      "GroundZeroBotLimit": 8
    }
  },
  {
    "Name": "starting-pmcs-only-quietraids",
  	"PMCBotLimitPresets": {
      "FactoryBotLimit": 6,
      "InterchangeBotLimit": 8,
      "LaboratoryBotLimit": 6,
      "LighthouseBotLimit": 6,
      "ReserveBotLimit": 7,
      "ShorelineBotLimit": 7,
      "WoodsBotLimit": 8,
      "CustomsBotLimit": 7,
      "TarkovStreetsBotLimit": 7,
      "GroundZeroBotLimit": 8
    },
    "SCAVBotLimitPresets": {
      "FactoryBotLimit": 6,
      "InterchangeBotLimit": 8,
      "LaboratoryBotLimit": 6,
      "LighthouseBotLimit": 8,
      "ReserveBotLimit": 7,
      "ShorelineBotLimit": 7,
      "WoodsBotLimit": 10,
      "CustomsBotLimit": 7,
      "TarkovStreetsBotLimit": 7,
      "GroundZeroBotLimit": 8
    }
  },
  {
    "Name": "scav-raids",
  	"PMCBotLimitPresets": {
      "FactoryBotLimit": 6,
      "InterchangeBotLimit": 8,
      "LaboratoryBotLimit": 6,
      "LighthouseBotLimit": 6,
      "ReserveBotLimit": 7,
      "ShorelineBotLimit": 7,
      "WoodsBotLimit": 8,
      "CustomsBotLimit": 7,
      "TarkovStreetsBotLimit": 7,
      "GroundZeroBotLimit": 8
    },
    "SCAVBotLimitPresets": {
      "FactoryBotLimit": 6,
      "InterchangeBotLimit": 8,
      "LaboratoryBotLimit": 6,
      "LighthouseBotLimit": 8,
      "ReserveBotLimit": 7,
      "ShorelineBotLimit": 7,
      "WoodsBotLimit": 10,
      "CustomsBotLimit": 7,
      "TarkovStreetsBotLimit": 7,
      "GroundZeroBotLimit": 8
    }
  }
]
